src/__init__.py
src/const.py
src/errors.py
src/main/__init__.py
src/main/main.py
src/main/output_selector.py
src/output_processor/__init__.py
src/output_processor/dict.py
src/output_processor/dict_processor.py
src/output_processor/img.py
src/output_processor/translate.py
src/output_processor/webtools.py
test/__init__.py
test/main/__init__.py
test/main/test_main.py
test/main/test_output_selector.py
test/output_processor/__init__.py
test/output_processor/test_dict.py
test/output_processor/test_dict_processor.py
test/output_processor/test_img.py
test/output_processor/test_translation.py
eexpressor-1.0.dist-info/METADATA
eexpressor-1.0.dist-info/WHEEL
eexpressor-1.0.dist-info/top_level.txt
eexpressor-1.0.dist-info/RECORD
