Metadata-Version: 2.1
Name: eexpressor
Version: 1.0
Summary: Emotion expressor
Home-page: https://github.com/yangkyeongmo/eexpressor
Author: Yang Gyeongmo
Author-email: kyeongmo31@gmail.com
License: UNKNOWN
Keywords: emotion expressor
Platform: UNKNOWN
Requires-Python: >=3
